odoo/addons/shopinvader_api_security_invoice/README.rst
odoo/addons/shopinvader_api_security_invoice/__init__.py
odoo/addons/shopinvader_api_security_invoice/__manifest__.py
odoo/addons/shopinvader_api_security_invoice/i18n/shopinvader_api_security_invoice.pot
odoo/addons/shopinvader_api_security_invoice/readme/CONTRIBUTORS.rst
odoo/addons/shopinvader_api_security_invoice/readme/DESCRIPTION.rst
odoo/addons/shopinvader_api_security_invoice/security/acl_product_product.xml
odoo/addons/shopinvader_api_security_invoice/security/acl_product_template.xml
odoo/addons/shopinvader_api_security_invoice/security/acl_uom_uom.xml
odoo/addons/shopinvader_api_security_invoice/security/groups.xml
odoo/addons/shopinvader_api_security_invoice/security/rule+acl_account_move.xml
odoo/addons/shopinvader_api_security_invoice/security/rule+acl_account_move_line.xml
odoo/addons/shopinvader_api_security_invoice/static/description/index.html
odoo_addon_shopinvader_api_security_invoice-16.0.1.0.1.dist-info/METADATA
odoo_addon_shopinvader_api_security_invoice-16.0.1.0.1.dist-info/WHEEL
odoo_addon_shopinvader_api_security_invoice-16.0.1.0.1.dist-info/top_level.txt
odoo_addon_shopinvader_api_security_invoice-16.0.1.0.1.dist-info/RECORD
