Metadata-Version: 2.1
Name: odoo-addon-shopinvader_api_security_invoice
Version: 16.0.1.0.1
Summary: Add security rule to expose invoices
Home-page: https://github.com/shopinvader/odoo-shopinvader
Author: Camptocamp, Odoo Community Association (OCA)
Author-email: support@odoo-community.org
License: AGPL-3
Classifier: Programming Language :: Python
Classifier: Framework :: Odoo
Classifier: Framework :: Odoo :: 16.0
Classifier: License :: OSI Approved :: GNU Affero General Public License v3
Classifier: Development Status :: 3 - Alpha
Requires-Python: >=3.10
Requires-Dist: odoo-addon-fastapi<16.1dev,>=16.0dev
Requires-Dist: odoo<16.1dev,>=16.0a
